codebased/GREETING.txt
codebased/__init__.py
codebased/background_worker.py
codebased/constants.py
codebased/editor.py
codebased/embeddings.py
codebased/exceptions.py
codebased/filesystem.py
codebased/gitignore.py
codebased/index.py
codebased/main.py
codebased/migrations/000_initial.sql
codebased/models.py
codebased/parser.py
codebased/search.py
codebased/settings.py
codebased/stats.py
codebased/storage.py
codebased/tui.py
codebased/utils.py
codebased-0.6.2.dist-info/LICENSE
codebased-0.6.2.dist-info/METADATA
codebased-0.6.2.dist-info/WHEEL
codebased-0.6.2.dist-info/entry_points.txt
codebased-0.6.2.dist-info/RECORD
