Metadata-Version: 2.1
Name: codebased
Version: 0.6.2
Summary: AI-powered code search for the terminal and beyond.
Home-page: https://github.com/codebased-sh/codebased
Author: Max Conradt
Author-email: mhconradt@protonmail.com
Requires-Python: >=3.9,<4.0
Classifier: Programming Language :: Python :: 3
Classifier: Programming Language :: Python :: 3.9
Classifier: Programming Language :: Python :: 3.10
Classifier: Programming Language :: Python :: 3.11
Classifier: Programming Language :: Python :: 3.12
Requires-Dist: chardet (>=5.2.0,<6.0.0)
Requires-Dist: colorama (>=0.4.6,<0.5.0)
Requires-Dist: faiss-cpu (>=1.8.0.post1,<2.0.0)
Requires-Dist: openai (>=1.42.0,<2.0.0)
Requires-Dist: textual (>=0.79.1,<0.80.0)
Requires-Dist: tiktoken (>=0.7.0,<0.8.0)
Requires-Dist: toml (>=0.10.2,<0.11.0)
Requires-Dist: tree-sitter (>=0.23,<0.24)
Requires-Dist: tree-sitter-c (>=0.23,<0.24)
Requires-Dist: tree-sitter-c-sharp (>=0.23,<0.24)
Requires-Dist: tree-sitter-cpp (>=0.23,<0.24)
Requires-Dist: tree-sitter-go (>=0.23,<0.24)
Requires-Dist: tree-sitter-java (>=0.23,<0.24)
Requires-Dist: tree-sitter-javascript (>=0.23,<0.24)
Requires-Dist: tree-sitter-php (>=0.23,<0.24)
Requires-Dist: tree-sitter-python (>=0.23,<0.24)
Requires-Dist: tree-sitter-ruby (>=0.23,<0.24)
Requires-Dist: tree-sitter-rust (>=0.23,<0.24)
Requires-Dist: tree-sitter-typescript (>=0.23,<0.24)
Requires-Dist: typer (>=0.12.5,<0.13.0)
Requires-Dist: watchdog (>=5.0.0,<6.0.0)
Project-URL: Repository, https://github.com/codebased-sh/codebased
